Lab2/Part2/src/clk_divider.vhd
LIBRARY ieee;
USE ieee.std_logic_1164.ALL;
USE ieee.numeric_std.ALL;

ENTITY clk_divider IS
  PORT (
    clk_in  : IN STD_LOGIC;
    clk_out : OUT STD_LOGIC
  );
END ENTITY;

ARCHITECTURE behavioral OF clk_divider IS
  SIGNAL count : INTEGER := 1;
BEGIN

  PROCESS (clk_in)
  BEGIN
    IF rising_edge(clk_in) THEN
      count <= count + 1;
      IF count = 62500000 THEN
        clk_out <= NOT clk_out;
        count   <= 1;
      END IF;
    END IF;
  END PROCESS;

END ARCHITECTURE;

Lab2/Part2/src/vending_m.vhd

-----------------------------------------------------------------------------------------------------------
-- Company: Department of Electrical and Computer Engineering, University of Alberta
-- Engineer: Shyama Gandhi and Bruce Cockburn
--
-- Create Date: 10/11/2021 09:50:46 PM
-- Design Name:
-- Module Name: vending - Behavioral
-- Project Name:
-- Target Devices:
-- Tool Versions:
-- Description: VENDING MACHINE - LAB 2 : ECE 410 (2021)
--
-- Dependencies:
--
-- Revision:
-- Revision 0.01 - File Created
-- Additional Comments:
--*********************************************************************************
-- The Vending Machine accepts 1$, 2$ and 3$ denominations. soft drink price : 2$, granola bar : 4$
-- The current sum of the total money inserted should be displayed on the seven segment.
-- Hand over the change to the customer, and then dispense the item (soft drink/granola bar)
----------------------------------------------------------------------------------

-- 0: ABCDEF    "1111110"
-- 1: BC        "0110000"
-- 2: ABDEG     "1101101"
-- 3: ABCDG     "1111001"
-- 4: BCFG      "0110011"
-- 5: ACDFG     "1011O11"
-- 6: ACDEFG    "1011111"
-- 7: ABC       "1110000"
-- 8: ABCDEFG   "1111111"
-- 9: ABCFG     "1110011"

LIBRARY IEEE;
USE IEEE.STD_LOGIC_1164.ALL;
USE ieee.numeric_std.ALL;
ENTITY vending_m IS
  PORT (
    clk        : IN STD_LOGIC;
    reset      : IN STD_LOGIC;
    item_sel   : IN STD_LOGIC;                     -- sel=0 for soft drink (2$), sel=1 for granola bar (4$)
    coins_in   : IN STD_LOGIC_VECTOR(1 DOWNTO 0);  -- "00" - 0$, "01" - 1$, "10" - 2$, "11" - 3$
    change_out : OUT STD_LOGIC_VECTOR(1 DOWNTO 0); -- changeout is displayed on two leds - "00" - 0$
    -- "01" - 1$, "10" - 2$ and "11" - 3$
    display_sum    : OUT STD_LOGIC_VECTOR(6 DOWNTO 0); -- display the current sum of inserted money on the seven segment
    select_segment : OUT STD_LOGIC;                    -- select the left or right segment
    soft_drink     : OUT STD_LOGIC;                    -- turn on the LED to dispense soft drink
    granola_bar    : OUT STD_LOGIC);                   -- turn on the LED to dispense granola bar

END vending_m;

ARCHITECTURE Behavioral OF vending_m IS
  ---------------------------------------------
  -- *** Add the clk_divider component here
  -- Remember, you want to add this component here and then use it later when you wish to have the divided clock by a factor of 62500000
  COMPONENT clk_divider IS
    PORT (
      clk_in  : IN STD_LOGIC;
      clk_out : OUT STD_LOGIC);
  END COMPONENT;
  ---------------------------------------------

  SIGNAL clk_o : STD_LOGIC;
  TYPE state_type IS (sum_0, -- state names represent the total sum of inserted money by the user
    sum_1,
    sum_2,
    sum_3,
    sum_4,
    sum_5,
    sum_6,
    dispense);

  SIGNAL present_state, next_state : state_type; -- current and next state declaration.

BEGIN

  ---------------------------------------------
  -- *** port map the clk_divider here
  clkdiv : clk_divider
  PORT MAP(
    clk_in  => clk,
    clk_out => clk_o);
  ---------------------------------------------

  select_segment <= '0'; -- you may use either the left or the right seven segment.

  --  the process below uses the 'clk' i.e. the undivided clock , i.e. the clock signal from the entity.
  --  you can replace it with the divided clock signal later on when you add the 'clk_divider' component.
  --  same way, you will need to change the clock signal in the 'elsif' statement inside the process below, later on!

  PROCESS (clk_o, reset)
  BEGIN
    IF (reset = '1') THEN
      ---------------------------------------------
      -- *** write one line of code to update the present state when reset=1
      present_state <= sum_0;
      ---------------------------------------------
    ELSIF (rising_edge(clk_o)) THEN
      ---------------------------------------------
      -- *** write one line of code to update the present state
      present_state <= next_state;
      ---------------------------------------------
    END IF;
  END PROCESS;

  PROCESS (present_state, coins_in) --*** complete the sensitivity list
  BEGIN
    CASE present_state IS
      WHEN sum_0 =>
        soft_drink  <= '0';
        granola_bar <= '0';
        change_out  <= "00";
        ---------------------------------------------
        --*** write one line of code to display the current sum of inserted money on the seven segment display
        ---------------------------------------------
        display_sum <= "1111110";
        ---------------------------------------------
        --*** update the design lines when coins inserted are 00/01/10/11
        -- you may use any conditional assignment format
        -- based on the inserted coins, update the next state
        -- for example, if the coins inserted is "10" i.e., 2$, go to state sum_2.

        CASE coins_in IS
          WHEN "00"   => next_state   <= sum_0;
          WHEN "01"   => next_state   <= sum_1;
          WHEN "10"   => next_state   <= sum_2;
          WHEN "11"   => next_state   <= sum_3;
          WHEN OTHERS => next_state <= sum_0;
        END CASE;
        ---------------------------------------------

      WHEN sum_1 =>
        soft_drink  <= '0';
        granola_bar <= '0';
        change_out  <= "00";

        ---------------------------------------------
        --*** write one line of code to display the current sum of inserted money on the seven segment display
        ---------------------------------------------
        display_sum <= "0110000";
        ---------------------------------------------
        --*** update the design lines when coins inserted are 00/01/10/11
        -- you may use any conditional assignment format
        -- based on the inserted coins, update the next state
        -- for example, if the coins inserted is "10" i.e., 2$,
        -- the total amount inserted till now is 2$ + 1$ = 3$. So, you wish to update the next_state accordingly.
        -- For example, say, if item_sel=0, and user inserted 1$, so the total amount is 2$. The next state is now, sum_2.
        -- In this case inside sum_2, you now want to return if any change and then dispense the soft drink.
        -- Make sure, from "sum_2" to "sum_6", you also take care to even check if item_sel=0 or item_sel=1 and update the state accordingly. 
        CASE coins_in IS
          WHEN "00"   => next_state   <= sum_1;
          WHEN "01"   => next_state   <= sum_2;
          WHEN "10"   => next_state   <= sum_3;
          WHEN "11"   => next_state   <= sum_4;
          WHEN OTHERS => next_state <= sum_1;
        END CASE;
        ---------------------------------------------

      WHEN sum_2 =>
        soft_drink  <= '0';
        granola_bar <= '0';
        change_out  <= "00";

        ---------------------------------------------
        --*** write one line of code to display the current sum of inserted money on the seven segment display
        ---------------------------------------------
        display_sum <= "1101101";
        ---------------------------------------------
        --*** update the design lines when coins inserted are 00/01/10/11
        -- you may use any conditional assignment format
        -- based on the inserted coins, update the next state

        IF (item_sel = '0') THEN
          next_state <= dispense;
          change_out <= "00";
        ELSE
          CASE coins_in IS
            WHEN "00"   => next_state   <= sum_2;
            WHEN "01"   => next_state   <= sum_3;
            WHEN "10"   => next_state   <= sum_4;
            WHEN "11"   => next_state   <= sum_5;
            WHEN OTHERS => next_state <= sum_2;
          END CASE;
        END IF;
        ---------------------------------------------

      WHEN sum_3 =>
        soft_drink  <= '0';
        granola_bar <= '0';
        change_out  <= "00";

        ---------------------------------------------
        --*** write one line of code to display the current sum of inserted money on the seven segment display
        ---------------------------------------------
        display_sum <= "1111001";
        ---------------------------------------------
        --*** update the design lines when coins inserted are 00/01/10/11
        -- you may use any conditional assignment format
        -- based on the inserted coins, update the next state

        IF (item_sel = '0') THEN
          next_state <= sum_2;
          change_out <= "01";
        ELSE
          CASE coins_in IS
            WHEN "00"   => next_state   <= sum_3;
            WHEN "01"   => next_state   <= sum_4;
            WHEN "10"   => next_state   <= sum_5;
            WHEN "11"   => next_state   <= sum_6;
            WHEN OTHERS => next_state <= sum_3;
          END CASE;
        END IF;
        ---------------------------------------------

      WHEN sum_4 =>
        soft_drink  <= '0';
        granola_bar <= '0';

        ---------------------------------------------
        --*** write one line of code to display the current sum of inserted money on the seven segment display
        ---------------------------------------------
        display_sum <= "0110011";
        ---------------------------------------------
        --*** update the design lines when coins inserted are 00/01/10/11
        -- you may use any conditional assignment format
        -- based on the inserted coins, update the next state

        IF (item_sel = '0') THEN
          next_state <= sum_2;
          change_out <= "10";
        ELSE
          next_state <= dispense;
          change_out <= "00";
        END IF;
        ---------------------------------------------

      WHEN sum_5 =>
        soft_drink  <= '0';
        granola_bar <= '0';

        ---------------------------------------------
        --*** write one line of code to display the current sum of inserted money on the seven segment display
        ---------------------------------------------
        display_sum <= "1011011";
        ---------------------------------------------
        --*** update the design lines when coins inserted are 00/01/10/11
        -- you may use any conditional assignment format
        -- based on the inserted coins, update the next state

        next_state <= sum_4;
        change_out <= "01";
        ---------------------------------------------

      WHEN sum_6 =>
        soft_drink  <= '0';
        granola_bar <= '0';

        ---------------------------------------------
        --*** write one line of code to display the current sum of inserted money on the seven segment display
        ---------------------------------------------
        display_sum <= "1011111";
        ---------------------------------------------
        --*** update the design lines when coins inserted are 00/01/10/11
        -- you may use any conditional assignment format
        -- based on the inserted coins, update the next state

        next_state <= sum_4;
        change_out <= "10";
        ---------------------------------------------

      WHEN dispense =>
        change_out  <= "00";
        display_sum <= "0111111";

        IF (item_sel = '0') THEN
          ---------------------------------------------
          --** write two assignment statements to dispense the soft drink and granola bar
          soft_drink <= '1';
          ---------------------------------------------
        ELSE
          ---------------------------------------------
          --** write two assignment statements to dispense the soft drink and granola bar
          granola_bar <= '1';
          ---------------------------------------------
        END IF;
        next_state <= sum_0;

    END CASE;
  END PROCESS;
END Behavioral;

Lab2/Part2/test/vending_m_tb.vhd
LIBRARY IEEE;
USE IEEE.STD_LOGIC_1164.ALL;
USE std.env.finish;

-- Uncomment the following library declaration if using
-- arithmetic functions with Signed or Unsigned values
--use IEEE.NUMERIC_STD.ALL;

-- Uncomment the following library declaration if instantiating
-- any Xilinx leaf cells in this code.
--library UNISIM;
--use UNISIM.VComponents.all;

ENTITY vending_m_tb IS
END vending_m_tb;

ARCHITECTURE Behavioral OF vending_m_tb IS

  COMPONENT vending_m IS
    PORT (
      clk        : IN STD_LOGIC;
      reset      : IN STD_LOGIC;
      item_sel   : IN STD_LOGIC;                     -- sel=0 for soft drink (2$), sel=1 for granola bar (4$)
      coins_in   : IN STD_LOGIC_VECTOR(1 DOWNTO 0);  -- "00" - 0$, "01" - 1$, "10" - 2$, "11" - 3$
      change_out : OUT STD_LOGIC_VECTOR(1 DOWNTO 0); -- changeout is displayed on two leds - "00" - 0$
      -- "01" - 1$, "10" - 2$ and "11" - 3$
      display_sum    : OUT STD_LOGIC_VECTOR(6 DOWNTO 0); -- display the current sum of inserted money on the seven segment
      select_segment : OUT STD_LOGIC;                    -- select the left or right segment
      soft_drink     : OUT STD_LOGIC;                    -- turn on the LED to dispense soft drink
      granola_bar    : OUT STD_LOGIC);                   -- turn on the LED to dispense granola bar
  END COMPONENT;

  SIGNAL clk_design           : STD_LOGIC;
  SIGNAL rst                  : STD_LOGIC;
  SIGNAL item_select          : STD_LOGIC;
  SIGNAL coins                : STD_LOGIC_VECTOR(1 DOWNTO 0);
  SIGNAL change               : STD_LOGIC_VECTOR(1 DOWNTO 0);
  SIGNAL display              : STD_LOGIC_VECTOR(6 DOWNTO 0);
  SIGNAL segment              : STD_LOGIC;
  SIGNAL soft_drink_dispense  : STD_LOGIC;
  SIGNAL granola_bar_dispense : STD_LOGIC;
  SIGNAL dispensed            : STD_LOGIC_VECTOR(1 DOWNTO 0);

  CONSTANT clk_period : TIME := 40 ns;

BEGIN
  --*** add the design lines to port map the entity here
  VENDING_ENT : vending_m PORT MAP(
    clk            => clk_design,
    reset          => rst,
    item_sel       => item_select,
    coins_in       => coins,
    change_out     => change,
    display_sum    => display,
    select_segment => segment,
    soft_drink     => soft_drink_dispense,
    granola_bar    => granola_bar_dispense);
  --*** end design lines     
  --   dispensed <= "10";    

  clk_process : PROCESS
  BEGIN
    clk_design <= '0';
    WAIT FOR clk_period/2;
    clk_design <= '1';
    WAIT FOR clk_period/2;
  END PROCESS;

  stim_proc : PROCESS
  BEGIN

    rst <= '0';

    -- ****Test cases****
    -- Write the series of test cases here to verify the correct working of your design.
    -- Provide the input stimulus to the signals : item_select, coins

    --Testing cases where item_select = '0'
    item_select <= '0';
    coins       <= "01";
    WAIT UNTIL falling_edge(clk_design);

    coins <= "01";
    WAIT UNTIL falling_edge(clk_design);

    coins <= "00";
    WAIT UNTIL falling_edge(clk_design);

    ASSERT ((soft_drink_dispense = '1') AND (change = "00"))
    REPORT "soft_drink_dispense != 1 or change != 0" SEVERITY failure;
    WAIT UNTIL falling_edge(clk_design);

    coins <= "11";
    WAIT UNTIL falling_edge(clk_design);

    ASSERT (change = "01")
    REPORT "change != 1" SEVERITY failure;
    WAIT UNTIL falling_edge(clk_design);

    coins <= "00";
    WAIT UNTIL falling_edge(clk_design);

    ASSERT (soft_drink_dispense = '1')
    REPORT "soft_drink_dispense != 1" SEVERITY failure;
    WAIT UNTIL falling_edge(clk_design);

    item_select <= '1';
    coins       <= "01";
    WAIT UNTIL falling_edge(clk_design);

    coins <= "11";
    WAIT UNTIL falling_edge(clk_design);

    coins <= "00";
    WAIT UNTIL falling_edge(clk_design);

    ASSERT (granola_bar_dispense = '1')
    REPORT "granola_bar_dispense != 1" SEVERITY failure;
    WAIT UNTIL falling_edge(clk_design);

    coins <= "11";
    WAIT UNTIL falling_edge(clk_design);

    coins <= "11";
    WAIT UNTIL falling_edge(clk_design);

    ASSERT (change = "10")
    REPORT "change != 2" SEVERITY failure;
    WAIT UNTIL falling_edge(clk_design);

    coins <= "00";
    WAIT UNTIL falling_edge(clk_design);

    ASSERT (granola_bar_dispense = '1')
    REPORT "granola_bar_dispense != 1" SEVERITY failure;
    WAIT UNTIL falling_edge(clk_design);

    std.env.finish;
  END PROCESS;
END Behavioral;

Lab2/Part2/simulation/vending_m_tb.vcd
$date
  Sat Oct 30 21:03:29 2021
$end
$version
  GHDL v0
$end
$timescale
  1 fs
$end
$scope module standard $end
$upscope $end
$scope module textio $end
$upscope $end
$scope module std_logic_1164 $end
$upscope $end
$scope module env $end
$upscope $end
$scope module numeric_std $end
$upscope $end
$scope module vending_m_tb $end
$var reg 1 ! clk_design $end
$var reg 1 " rst $end
$var reg 1 # item_select $end
$var reg 2 $ coins[1:0] $end
$var reg 2 % change[1:0] $end
$var reg 7 & display[6:0] $end
$var reg 1 ' segment $end
$var reg 1 ( soft_drink_dispense $end
$var reg 1 ) granola_bar_dispense $end
$var reg 2 * dispensed[1:0] $end
$scope module vending_ent $end
$var reg 1 + clk $end
$var reg 1 , reset $end
$var reg 1 - item_sel $end
$var reg 2 . coins_in[1:0] $end
$var reg 2 / change_out[1:0] $end
$var reg 7 0 display_sum[6:0] $end
$var reg 1 1 select_segment $end
$var reg 1 2 soft_drink $end
$var reg 1 3 granola_bar $end
$var reg 1 4 clk_o $end
$comment present_state is not handled $end
$comment next_state is not handled $end
$upscope $end
$upscope $end
$enddefinitions $end
#0
0!
0"
0#
b01 $
b00 %
b1111110 &
0'
0(
0)
bUU *
0+
0,
0-
b01 .
b00 /
b1111110 0
01
02
03
U4
#20000000
1!
b0110000 &
1+
b0110000 0
#40000000
0!
0+
#60000000
1!
b1101101 &
1+
b1101101 0
#80000000
0!
b00 $
0+
b00 .
#100000000
1!
b0111111 &
1(
1+
b0111111 0
12
#120000000
0!
0+
#140000000
1!
b1111110 &
0(
1+
b1111110 0
02
#160000000
0!
b11 $
0+
b11 .
#180000000
1!
b01 %
b1111001 &
1+
b01 /
b1111001 0
#200000000
0!
0+
#220000000
1!
b00 %
b1101101 &
1+
b00 /
b1101101 0
#240000000
0!
b00 $
0+
b00 .
#260000000
1!
b0111111 &
1(
1+
b0111111 0
12
#280000000
0!
0+
#300000000
1!
b1111110 &
0(
1+
b1111110 0
02
#320000000
0!
1#
b01 $
0+
1-
b01 .
#340000000
1!
b0110000 &
1+
b0110000 0
#360000000
0!
b11 $
0+
b11 .
#380000000
1!
b0110011 &
1+
b0110011 0
#400000000
0!
b00 $
0+
b00 .
#420000000
1!
b0111111 &
1)
1+
b0111111 0
13
#440000000
0!
0+
#460000000
1!
b1111110 &
0)
1+
b1111110 0
03
#480000000
0!
b11 $
0+
b11 .
#500000000
1!
b1111001 &
1+
b1111001 0
#520000000
0!
0+
#540000000
1!
b10 %
b1011111 &
1+
b10 /
b1011111 0
#560000000
0!
0+
#580000000
1!
b00 %
b0110011 &
1+
b00 /
b0110011 0
#600000000
0!
b00 $
0+
b00 .
#620000000
1!
b0111111 &
1)
1+
b0111111 0
13
#640000000
0!
0+
#660000000
1!
b1111110 &
0)
1+
b1111110 0
03
