Lab2/Part1/src/seq_fsm.vhd
---- Company: Department of Electrical and Computer Engineering, University of Alberta
---- Engineer: Shyama Gandhi and Bruce Cockburn
---- 
---- Create Date: 10/10/2021 03:41:32 PM
---- Design Name: 
---- Module Name: seq_fsm - Behavioral
---- Project Name: 
---- Target Devices: Zybo Z7-10 
---- Tool Versions: 
---- Description: SEQUENCE DETECTOR : 11011 - OVERLAPPING CASE : MEALY FSM
---- 
---- Dependencies: 
---- 
---- Revision:
---- Revision 0.01 - File Created

------------------------------------------------------------------------------------
---- Additional Comments:
---- ADD THE CODE IN THE COMMENTED SECTION. THERE ARE TWO INTENTIONAL MISTAKES TOO IN THIS CODE TEMPLATE! 
---- CORRECT THE MISTAKES TO ENSURE CORRECT WORKING OF FSM.

LIBRARY IEEE;
USE IEEE.STD_LOGIC_1164.ALL;

ENTITY seq_fsm IS
  PORT (
    clk           : IN STD_LOGIC;
    reset         : IN STD_LOGIC;
    seq_in        : IN STD_LOGIC;
    output_detect : OUT STD_LOGIC);
END seq_fsm;

ARCHITECTURE Behavioral OF seq_fsm IS

  SIGNAL clk_o : STD_LOGIC;

  TYPE states IS (A, B, C, D, E);
  SIGNAL state_reg, state_next : states;

  ---------------------------------------------
  -- Add the clk_divider component here
  -- Remember, you want to add this component here and then use it later when you wish to have the divided clock by a factor of 62500000
  --component clk_divider is
  --    port (
  --        clk_in  : in std_logic;
  --        clk_out : out std_logic        
  --    );
  --end component;

  ---------------------------------------------

BEGIN
  ---------------------------------------------
  -- port map the clk_divider here
  --clkdiv: component clk_divider
  --    port map (
  --        clk_in    => clk,
  --        clk_out   => clk_o    
  --    );

  ---------------------------------------------

  -- the process below uses the 'clk' i.e. the undivided clock , i.e. the clock signal from the entity.
  -- you can replace it with the divided clock signal later on when you add the 'clk_divider' component.
  -- same way, you will need to change the clock signal in the 'elsif' statement inside the process below, later on!
  PROCESS (clk, reset)
  BEGIN
    IF (reset = '1') THEN
      state_reg <= A;
    ELSIF (rising_edge(clk)) THEN
      state_reg <= state_next;
    END IF;
  END PROCESS;

  PROCESS (state_reg, seq_in) -- complete the sensitivity list
  BEGIN
    CASE state_reg IS
      WHEN A =>
        IF seq_in = '0' THEN
          state_next    <= A;
          output_detect <= '0';
        ELSE
          state_next    <= B;
          output_detect <= '0';
        END IF;

        --- Add the remaining cases for other states here!
      WHEN B =>
        IF seq_in = '0' THEN
          state_next    <= A;
          output_detect <= '0';
        ELSE
          state_next    <= C;
          output_detect <= '0';
        END IF;

      WHEN C =>
        IF seq_in = '0' THEN
          state_next    <= D;
          output_detect <= '0';
        ELSE
          state_next    <= C;
          output_detect <= '0';
        END IF;

      WHEN D =>
        IF seq_in = '0' THEN
          state_next    <= A;
          output_detect <= '0';
        ELSE
          state_next    <= E;
          output_detect <= '0';
        END IF;

      WHEN E =>
        IF seq_in = '0' THEN
          state_next    <= A;
          output_detect <= '0';
        ELSE
          state_next    <= C;
          output_detect <= '1';
        END IF;

      WHEN OTHERS =>
        state_next    <= A;
        output_detect <= '0';

    END CASE;
  END PROCESS;

END Behavioral;

Lab2/Part1/test/seq_fsm_tb.vhd
----------------------------------------------------------------------------------
-- Company: Department of Electrical and Computer Engineering, University of Alberta
-- Engineer: Shyama Gandhi and Bruce Cockburn
-- 
-- Create Date: 10/10/2021 04:05:35 PM
-- Design Name: 
-- Module Name: seq_fsm_tb - Behavioral
-- Project Name: 
-- Target Devices: Zybo Z7-10 
-- Tool Versions: 
-- Description: SEQUENCE DETECTOR : 11011 - OVERLAPPING CASE : MEALY FSM
-- 
-- Dependencies: 
-- 
-- Revision:
-- Revision 0.01 - File Created
-- Additional Comments:
-- 
----------------------------------------------------------------------------------
LIBRARY IEEE;
USE IEEE.STD_LOGIC_1164.ALL;

ENTITY seq_fsm_tb IS
END seq_fsm_tb;

ARCHITECTURE Behavioral OF seq_fsm_tb IS

  COMPONENT seq_fsm IS
    PORT (
      clk           : IN STD_LOGIC;
      reset         : IN STD_LOGIC;
      seq_in        : IN STD_LOGIC;
      output_detect : OUT STD_LOGIC);
  END COMPONENT;

  SIGNAL clk_design       : STD_LOGIC;
  SIGNAL rst              : STD_LOGIC;
  SIGNAL sequence_in      : STD_LOGIC;
  SIGNAL fsm_detector_out : STD_LOGIC;
  CONSTANT clk_period     : TIME := 40 ns;

BEGIN
  --*** add the design lines to port map the entity here
  FSM_SEQ : seq_fsm PORT MAP(
    seq_in        => sequence_in,
    reset         => rst,
    output_detect => fsm_detector_out,
    clk           => clk_design);
  --*** end design lines                               
  clk_process : PROCESS
  BEGIN
    clk_design <= '0';
    WAIT FOR clk_period/2;
    clk_design <= '1';
    WAIT FOR clk_period/2;
  END PROCESS;

  stim_proc : PROCESS
  BEGIN

    -- test sequence : "011011010011101100"
    rst         <= '0';
    
    sequence_in <= '0';
    WAIT FOR clk_period;
    sequence_in <= '1';
    WAIT FOR clk_period;
    sequence_in <= '1';
    WAIT FOR clk_period;
    sequence_in <= '0';
    WAIT FOR clk_period;
    sequence_in <= '1';
    WAIT FOR clk_period;
    sequence_in <= '1';
    WAIT FOR clk_period;
    sequence_in <= '0';
    WAIT FOR clk_period;
    sequence_in <= '1';
    WAIT FOR clk_period;
--    sequence_in <= '0';
--    WAIT FOR clk_period;
--    sequence_in <= '0';
--    WAIT FOR clk_period;
--    sequence_in <= '1';
--    WAIT FOR clk_period;
--    sequence_in <= '1';
--    WAIT FOR clk_period;
--    sequence_in <= '1';
--    WAIT FOR clk_period;
--    sequence_in <= '0';
--    WAIT FOR clk_period;
--    sequence_in <= '1';
--    WAIT FOR clk_period;
--    sequence_in <= '1';
--    WAIT FOR clk_period;
--    sequence_in <= '0';
--    WAIT FOR clk_period;
--    sequence_in <= '0';
--    WAIT FOR clk_period;
--    std.env.finish;
  END PROCESS;
END Behavioral;

Lab2/Part1/simulation/seq_fsm_tb.vcd
$date
  Thu Oct 28 20:30:58 2021
$end
$version
  GHDL v0
$end
$timescale
  1 fs
$end
$scope module standard $end
$upscope $end
$scope module textio $end
$upscope $end
$scope module std_logic_1164 $end
$upscope $end
$scope module env $end
$upscope $end
$scope module seq_fsm_tb $end
$var reg 1 ! clk_design $end
$var reg 1 " rst $end
$var reg 1 # sequence_in $end
$var reg 1 $ fsm_detector_out $end
$scope module fsm_seq $end
$var reg 1 % clk $end
$var reg 1 & reset $end
$var reg 1 ' seq_in $end
$var reg 1 ( output_detect $end
$var reg 1 ) clk_o $end
$comment state_reg is not handled $end
$comment state_next is not handled $end
$upscope $end
$upscope $end
$enddefinitions $end
#0
0!
0"
0#
0$
0%
0&
0'
0(
U)
#20000000
1!
1%
#40000000
0!
1#
0%
1'
#60000000
1!
1%
#80000000
0!
0%
#100000000
1!
1%
#120000000
0!
0#
0%
0'
#140000000
1!
1%
#160000000
0!
0%
#180000000
1!
1%
#200000000
0!
1#
0%
1'
#220000000
1!
1%
#240000000
0!
0#
0%
0'
#260000000
1!
1%
#280000000
0!
1#
0%
1'
#300000000
1!
1%
#320000000
0!
0#
0%
0'
#340000000
1!
1%
#360000000
0!
0%
#380000000
1!
1%
#400000000
0!
1#
0%
1'
#420000000
1!
1%
#440000000
0!
0%
#460000000
1!
1%
#480000000
0!
0%
#500000000
1!
1%
#520000000
0!
0#
0%
0'
#540000000
1!
1%
#560000000
0!
1#
0%
1'
#580000000
1!
1$
1%
1(
#600000000
0!
0%
#620000000
1!
0$
1%
0(
#640000000
0!
0#
0%
0'
