Lab1/src/S0_mux.vhd
----------------------------------------------------------------------------------
-- Company: Department of Electrical and Computer Engineering, University of Alberta
-- Engineer: Shyama Gandhi and Bruce Cockburn
-- 
-- Create Date: 08/10/2020 11:28:43 AM
-- Design Name: 
-- Module Name: s0_16_1_mux - Behavioral
-- Project Name: 
-- Target Devices: 
-- Tool Versions: 
-- Description: 
-- 
-- Dependencies: 
-- 
-- Revision:
-- Revision 0.01 - File Created
-- Additional Comments:
-- 
----------------------------------------------------------------------------------
LIBRARY IEEE;
USE IEEE.STD_LOGIC_1164.ALL;

-- Uncomment the following library declaration if using
-- arithmetic functions with Signed or Unsigned values
--use IEEE.NUMERIC_STD.ALL;

-- Uncomment the following library declaration if instantiating
-- any Xilinx leaf cells in this code.
--library UNISIM;
--use UNISIM.VComponents.all;

ENTITY S0_mux IS
  PORT (
    cin       : IN STD_LOGIC;
    select_in : IN STD_LOGIC_VECTOR(3 DOWNTO 0);
    y_s0      : OUT STD_LOGIC);
END S0_mux;

ARCHITECTURE Behavioral OF S0_mux IS

BEGIN
  PROCESS (cin, select_in)
  BEGIN
    -- write the input line functions generated for 16:1 to derive the S(0) output.
    -- The input lines can be '0' / '1' / Cin / (not) Cin.
    -- It is possible to use if...else or case statements here. 
    CASE select_in IS
      WHEN "0000" => y_s0 <= Cin;
      WHEN "0001" => y_s0 <= NOT Cin;
      WHEN "0010" => y_s0 <= Cin;
      WHEN "0011" => y_s0 <= NOT Cin;
      WHEN "0100" => y_s0 <= NOT Cin;
      WHEN "0101" => y_s0 <= Cin;
      WHEN "0110" => y_s0 <= NOT Cin;
      WHEN "0111" => y_s0 <= Cin;
      WHEN "1000" => y_s0 <= Cin;
      WHEN "1001" => y_s0 <= NOT Cin;
      WHEN "1010" => y_s0 <= Cin;
      WHEN "1011" => y_s0 <= NOT Cin;
      WHEN "1100" => y_s0 <= NOT Cin;
      WHEN "1101" => y_s0 <= Cin;
      WHEN "1110" => y_s0 <= NOT Cin;
      WHEN "1111" => y_s0 <= Cin;
      WHEN OTHERS => y_s0 <= '-';

        -- Write the VHDL codes for all the input cases.
    END CASE;
  END PROCESS;

END Behavioral;

Lab1/src/S1_mux.vhd
----------------------------------------------------------------------------------
-- Company: Department of Electrical and Computer Engineering, University of Alberta
-- Engineer: Shyama Gandhi and Bruce Cockburn
-- 
-- Create Date: 08/10/2020 11:28:43 AM
-- Design Name: 
-- Module Name: s1_16_1_mux - Behavioral
-- Project Name: 
-- Target Devices: 
-- Tool Versions: 
-- Description: 
-- 
-- Dependencies: 
-- 
-- Revision:
-- Revision 0.01 - File Created
-- Additional Comments:
-- 
----------------------------------------------------------------------------------


library IEEE;
use IEEE.STD_LOGIC_1164.ALL;

-- Uncomment the following library declaration if using
-- arithmetic functions with Signed or Unsigned values
--use IEEE.NUMERIC_STD.ALL;

-- Uncomment the following library declaration if instantiating
-- any Xilinx leaf cells in this code.
--library UNISIM;
--use UNISIM.VComponents.all;

entity S1_mux is
  Port ( cin        : in std_logic;
         select_in  : in std_logic_vector(3 downto 0);
         y_s1       : out std_logic );
end S1_mux;

architecture Behavioral of S1_mux is

begin
    process(cin,select_in)
    begin
    -- write the input line functions generated for 16:1 to derive the S(1) output.
    -- The input lines can be '0' / '1' / Cin / (not) Cin.
    -- It is possible to use if...else or case statements here. 
    case select_in is 
    when "0000" =>   y_s1 <= '0';
    when "0001" =>   y_s1 <= cin;
    when "0010" =>   y_s1 <= '1';
    when "0011" =>   y_s1 <= not cin;
    when "0100" =>   y_s1 <= cin;
    when "0101" =>   y_s1 <= '1';
    when "0110" =>   y_s1 <= not cin;
    when "0111" =>   y_s1 <= '0';
    when "1000" =>   y_s1 <= '1';
    when "1001" =>   y_s1 <= not cin;
    when "1010" =>   y_s1 <= '0';
    when "1011" =>   y_s1 <= cin;
    when "1100" =>   y_s1 <= not cin;
    when "1101" =>   y_s1 <= '0';
    when "1110" =>   y_s1 <= cin ;
    when "1111" =>   y_s1 <= '1';
    -- Write the VHDL codes for all the input cases.
    end case;    
    end process;

end Behavioral;

Lab1/src/Co_mux.vhd
----------------------------------------------------------------------------------
-- Company: Department of Electrical and Computer Engineering, University of Alberta
-- Engineer: Shyama Gandhi and Bruce Cockburn
-- 
-- Create Date: 08/10/2020 11:28:43 AM
-- Design Name: 
-- Module Name: cout_16_1_mux - Behavioral
-- Project Name: 
-- Target Devices: 
-- Tool Versions: 
-- Description: 
-- 
-- Dependencies: 
-- 
-- Revision:
-- Revision 0.01 - File Created
-- Additional Comments:
-- 
----------------------------------------------------------------------------------
LIBRARY IEEE;
USE IEEE.STD_LOGIC_1164.ALL;

-- Uncomment the following library declaration if using
-- arithmetic functions with Signed or Unsigned values
--use IEEE.NUMERIC_STD.ALL;

-- Uncomment the following library declaration if instantiating
-- any Xilinx leaf cells in this code.
--library UNISIM;
--use UNISIM.VComponents.all;

ENTITY Co_mux IS
  PORT (
    cin       : IN STD_LOGIC;
    select_in : IN STD_LOGIC_VECTOR(3 DOWNTO 0);
    y_cout    : OUT STD_LOGIC);
END Co_mux;

ARCHITECTURE Behavioral OF Co_mux IS

BEGIN
  PROCESS (cin, select_in)
  BEGIN
    -- write the input line functions generated for 16:1 to derive the carry output.
    -- The input lines can be '0' / '1' / Cin / (not) Cin.
    -- It is possible to use if...else or case statements here.
    CASE select_in IS
      WHEN "0000" => y_cout <= '0';
      WHEN "0001" => y_cout <= '0';
      WHEN "0010" => y_cout <= '0';
      WHEN "0011" => y_cout <= Cin;
      WHEN "0100" => y_cout <= '0';
      WHEN "0101" => y_cout <= '0';
      WHEN "0110" => y_cout <= Cin;
      WHEN "0111" => y_cout <= '1';
      WHEN "1000" => y_cout <= '0';
      WHEN "1001" => y_cout <= Cin;
      WHEN "1010" => y_cout <= '1';
      WHEN "1011" => y_cout <= '1';
      WHEN "1100" => y_cout <= Cin;
      WHEN "1101" => y_cout <= '1';
      WHEN "1110" => y_cout <= '1';
      WHEN "1111" => y_cout <= '1';
      WHEN OTHERS => y_cout <= '-';
        -- Write the VHDL codes for all the input cases.

    END CASE;
  END PROCESS;

END Behavioral;

Lab1/src/full_adder_2bit.vhd
----------------------------------------------------------------------------------
-- Company: Department of Electrical and Computer Engineering, University of Alberta
-- Engineer: Shyama Gandhi and Bruce Cockburn
-- 
-- Create Date: 08/10/2020 10:04:58 AM
-- Design Name: 
-- Module Name: fa_2bit - Behavioral
-- Project Name: 
-- Target Devices: 
-- Tool Versions: 
-- Description: 2-BIT FULL ADDER CREATED USING THREE 16:1 MULTIPLEXERS each for carry out, S(1) and S(0).
--  The components for S0, S1 and C0 are to be included in this top module using the port map statements.

-- 
-- Dependencies: 
-- 
-- Revision:
-- Revision 0.01 - File Created
-- Additional Comments:
-- 
----------------------------------------------------------------------------------
LIBRARY IEEE;
USE IEEE.STD_LOGIC_1164.ALL;

-- Uncomment the following library declaration if using
-- arithmetic functions with Signed or Unsigned values
--use IEEE.NUMERIC_STD.ALL;

-- Uncomment the following library declaration if instantiating
-- any Xilinx leaf cells in this code.
--library UNISIM;
--use UNISIM.VComponents.all;

ENTITY full_adder_2bit IS
  PORT (
    A              : IN STD_LOGIC_VECTOR(1 DOWNTO 0); --input vector A
    B              : IN STD_LOGIC_VECTOR(1 DOWNTO 0); --input vector B
    C_in           : IN STD_LOGIC;                    --CARRY INPUT : 0/1
    Sum            : OUT STD_LOGIC_VECTOR(1 DOWNTO 0);--sum output
    C_out          : OUT STD_LOGIC;                     --carry output
    compare_result : OUT STD_LOGIC_VECTOR(2 DOWNTO 0)); -- compare the input vector A and B : mapped to RGB led in xdc file
END full_adder_2bit;

ARCHITECTURE Behavioral OF full_adder_2bit IS

  COMPONENT Co_mux IS
    PORT (
      cin       : IN STD_LOGIC;
      select_in : IN STD_LOGIC_VECTOR(3 DOWNTO 0);
      y_cout    : OUT STD_LOGIC);
  END COMPONENT;

  COMPONENT S1_mux IS
    PORT (
      cin       : IN STD_LOGIC;
      select_in : IN STD_LOGIC_VECTOR(3 DOWNTO 0);
      y_s1      : OUT STD_LOGIC);
  END COMPONENT;

  COMPONENT S0_mux IS
    PORT (
      cin       : IN STD_LOGIC;
      select_in : IN STD_LOGIC_VECTOR(3 DOWNTO 0);
      y_s0      : OUT STD_LOGIC);
  END COMPONENT;

BEGIN

  -- PART 3....
  -- The "LD6" - RGB led on board is used as an indication if A>B or A<B or A=B. 
  -- Write 3 lines of conditional signal assignment code (say using "WHEN/ELSE")
  -- to turn the LED red when A>B, green when A<B and blue when A=B.

  -- port map the component for generating carry output                     
  carry_map : Co_mux PORT MAP(
    cin                   => C_in,
    select_in(3 DOWNTO 2) => A,
    select_in(1 DOWNTO 0) => B,
    y_cout                => C_out);

  -- port map the component for generating the S(1)
  s1map : S1_mux PORT MAP(
    cin                   => C_in,
    select_in(3 DOWNTO 2) => A,
    select_in(1 DOWNTO 0) => B,
    y_s1                  => Sum(1));
  -- port map the component for generating the S(0)                                    
  s0map : S0_mux PORT MAP(
    cin                   => C_in,
    select_in(3 DOWNTO 2) => A,
    select_in(1 DOWNTO 0) => B,
    y_s0                  => Sum(0));

END Behavioral;

Lab1/test/full_adder_2bit_tb.vhd
----------------------------------------------------------------------------------
-- Company: 
-- Engineer: 
-- 
-- Create Date: 10/03/2021 11:20:10 AM
-- Design Name: 
-- Module Name: full_adder_2bit_tb - Behavioral
-- Project Name: 
-- Target Devices: 
-- Tool Versions: 
-- Description: 
-- 
-- Dependencies: 
-- 
-- Revision:
-- Revision 0.01 - File Created
-- Additional Comments:
-- 
----------------------------------------------------------------------------------
LIBRARY IEEE;
USE IEEE.STD_LOGIC_1164.ALL;
USE std.env.finish;

-- Uncomment the following library declaration if using
-- arithmetic functions with Signed or Unsigned values
--use IEEE.NUMERIC_STD.ALL;

-- Uncomment the following library declaration if instantiating
-- any Xilinx leaf cells in this code.
--library UNISIM;
--use UNISIM.VComponents.all;

ENTITY full_adder_2bit_tb IS
  --  Port ( );
END full_adder_2bit_tb;

ARCHITECTURE Behavioral OF full_adder_2bit_tb IS

  COMPONENT full_adder_2bit IS
    PORT (
      A              : IN STD_LOGIC_VECTOR (1 DOWNTO 0);
      B              : IN STD_LOGIC_VECTOR (1 DOWNTO 0);
      c_in           : IN STD_LOGIC;
      sum            : OUT STD_LOGIC_VECTOR (1 DOWNTO 0);
      c_out          : OUT STD_LOGIC;
      compare_result : OUT STD_LOGIC_VECTOR(2 DOWNTO 0));
  END COMPONENT;

  SIGNAL A, B           : STD_LOGIC_VECTOR(1 DOWNTO 0);
  SIGNAL c_in, c_out    : STD_LOGIC;
  SIGNAL sum            : STD_LOGIC_VECTOR(1 DOWNTO 0);
  SIGNAL compare_result : STD_LOGIC_VECTOR(2 DOWNTO 0);

BEGIN
  Full_adder : full_adder_2bit PORT MAP(
    A              => A,
    B              => B,
    c_in           => c_in,
    sum            => Sum,
    c_out          => c_out,
    compare_result => compare_result
  );
  PROCESS
    CONSTANT time_period : TIME := 20 ns;

  BEGIN

    -- this is a self checking testbench written for few input combinations of the 2-bit half adder.
    -- Error in Sum and Cout will be reported using this self checking test bench
    -- On generation of the wrong outputs, error is reported in the tcl console window

    -- You must include reasonable number of test cases to verify the working of your design.

    -- Testing when B = 00
    ----------------
    A    <= "00";
    B    <= "00";
    c_in <= '0';
    WAIT FOR time_period;
    ASSERT ((sum = "00") AND (c_out = '0') AND (compare_result = "010")) --If for A=00 AND B=00, IF S!=00 AND C!=0, then there is an error
    REPORT "Error for input A_in=00 and B_in=00" SEVERITY error;
    ----------------
    ----------------
    A    <= "01";
    B    <= "00";
    c_in <= '1';
    WAIT FOR time_period;
    ASSERT ((sum = "10") AND (c_out = '0') AND (compare_result = "100")) --If for A=01 AND B=00, IF S!=10 AND C!=0, then there is an error
    REPORT "Error for input A_in=01 and B_in=00 " SEVERITY error;
    ----------------
    ----------------
    A    <= "10";
    B    <= "00";
    c_in <= '0';
    WAIT FOR time_period;
    ASSERT ((sum = "10") AND (c_out = '0') AND (compare_result = "100")) --If for A=10 AND B=00, IF S!=00 AND C!=0, then there is an error
    REPORT "Error for input A_in=10 and B_in=00" SEVERITY error;
    ----------------
    ----------------
    A    <= "11";
    B    <= "00";
    c_in <= '1';
    WAIT FOR time_period;
    ASSERT ((sum = "00") AND (c_out = '1') AND (compare_result = "100")) --If for A=11 AND B=00, IF S!=00 AND C!=1, then there is an error
    REPORT "Error for input A_in=11 and B_in=00" SEVERITY error;
    ----------------
    -- Testing when B = 01
    ----------------
    A    <= "00";
    B    <= "01";
    c_in <= '0';
    WAIT FOR time_period;
    ASSERT ((sum = "01") AND (c_out = '0') AND (compare_result = "001")) --If for A=00 AND B=01, IF S!=01 AND C!=0, then there is an error
    REPORT "Error for input A_in=00 and B_in=01" SEVERITY error;
    ----------------
    ----------------
    A    <= "01";
    B    <= "01";
    c_in <= '1';
    WAIT FOR time_period;
    ASSERT ((sum = "11") AND (c_out = '0') AND (compare_result = "010")) --If for A=01 AND B=01, IF S!=11 AND C!=0, then there is an error
    REPORT "Error for input A_in=01 and B_in=01" SEVERITY error;
    ----------------
    ----------------
    A    <= "10";
    B    <= "01";
    c_in <= '0';
    WAIT FOR time_period;
    ASSERT ((sum = "11") AND (c_out = '0') AND (compare_result = "100")) --If for A=10 AND B=01, IF S!=11 AND C!=0, then there is an error
    REPORT "Error for input A_in=10 and B_in=01" SEVERITY error;
    ----------------
    ----------------
    A    <= "11";
    B    <= "01";
    c_in <= '1';
    WAIT FOR time_period;
    ASSERT ((sum = "01") AND (c_out = '1') AND (compare_result = "100")) --If for A=11 AND B=01, IF S!=01 AND C!=1, then there is an error
    REPORT "Error for input A_in=11 and B_in=01" SEVERITY error;
    ----------------
    -- Testing when B = 10
    ----------------
    A    <= "00";
    B    <= "10";
    c_in <= '0';
    WAIT FOR time_period;
    ASSERT ((sum = "10") AND (c_out = '0') AND (compare_result = "001")) --If for A=00 AND B=10, IF S!=10 AND C!=0, then there is an error
    REPORT "Error for input A_in=00 and B_in=10" SEVERITY error;
    ----------------
    ----------------
    A    <= "01";
    B    <= "10";
    c_in <= '1';
    WAIT FOR time_period;
    ASSERT ((sum = "00") AND (c_out = '1') AND (compare_result = "001")) --If for A=01 AND B=10, IF S!=00 AND C!=0, then there is an error
    REPORT "Error for input A_in=01 and B_in=10 " SEVERITY error;
    ----------------
    ----------------
    A    <= "10";
    B    <= "10";
    c_in <= '0';
    WAIT FOR time_period;
    ASSERT ((sum = "00") AND (c_out = '1') AND (compare_result = "010")) --If for A=10 AND B=10, IF S!=00 AND C!=0, then there is an error
    REPORT "Error for input A_in=10 and B_in=10" SEVERITY error;
    ----------------
    ----------------
    A    <= "11";
    B    <= "10";
    c_in <= '1';
    WAIT FOR time_period;
    ASSERT ((sum = "10") AND (c_out = '1') AND (compare_result = "100")) --If for A=11 AND B=10, IF S!=00 AND C!=0, then there is an error
    REPORT "Error for input A_in=00 and B_in=00" SEVERITY error;
    ----------------
    -- Testing when B = 11
    ----------------
    A    <= "00";
    B    <= "11";
    c_in <= '0';
    WAIT FOR time_period;
    ASSERT ((sum = "11") AND (c_out = '0') AND (compare_result = "001")) --If for A=00 AND B=11, IF S!=00 AND C!=0, then there is an error
    REPORT "Error for input A_in=00 and B_in=00" SEVERITY error;
    ----------------
    ----------------
    A    <= "01";
    B    <= "11";
    c_in <= '1';
    WAIT FOR time_period;
    ASSERT ((sum = "01") AND (c_out = '1') AND (compare_result = "001")) --If for A=01 AND B=11, IF S!=00 AND C!=0, then there is an error
    REPORT "Error for input A_in=00 and B_in=00 " SEVERITY error;
    ----------------
    ----------------
    A    <= "10";
    B    <= "11";
    c_in <= '0';
    WAIT FOR time_period;
    ASSERT ((sum = "01") AND (c_out = '1') AND (compare_result = "001")) --If for A=10 AND B=11, IF S!=00 AND C!=0, then there is an error
    REPORT "Error for input A_in=00 and B_in=00" SEVERITY error;
    ----------------
    ----------------
    A    <= "11";
    B    <= "11";
    c_in <= '1';
    WAIT FOR time_period;
    ASSERT ((sum = "11") AND (c_out = '1') AND (compare_result = "010")) --If for A=11 AND B=11, IF S!=00 AND C!=0, then there is an error
    REPORT "Error for input A_in=00 and B_in=00" SEVERITY error;
    ----------------
    WAIT FOR time_period;

    finish;
  END PROCESS;

END Behavioral;

Lab1/simulation/full_adder_2bit_tb.vcd
$date
  Sun Oct 17 13:24:45 2021
$end
$version
  GHDL v0
$end
$timescale
  1 fs
$end
$scope module standard $end
$upscope $end
$scope module textio $end
$upscope $end
$scope module std_logic_1164 $end
$upscope $end
$scope module env $end
$upscope $end
$scope module numeric_std $end
$upscope $end
$scope module full_adder_2bit_tb $end
$var reg 2 ! a[1:0] $end
$var reg 2 " b[1:0] $end
$var reg 1 # c_in $end
$var reg 1 $ c_out $end
$var reg 2 % sum[1:0] $end
$var reg 3 & compare_result[2:0] $end
$scope module full_adder $end
$var reg 2 ' a[1:0] $end
$var reg 2 ( b[1:0] $end
$var reg 1 ) c_in $end
$var reg 2 * sum[1:0] $end
$var reg 1 + c_out $end
$var reg 3 , compare_result[2:0] $end
$scope module carry_map $end
$var reg 1 - cin $end
$var reg 4 . select_in[3:0] $end
$var reg 1 / y_cout $end
$upscope $end
$scope module s1map $end
$var reg 1 0 cin $end
$var reg 4 1 select_in[3:0] $end
$var reg 1 2 y_s1 $end
$upscope $end
$scope module s0map $end
$var reg 1 3 cin $end
$var reg 4 4 select_in[3:0] $end
$var reg 1 5 y_s0 $end
$upscope $end
$upscope $end
$upscope $end
$enddefinitions $end
#0
b00 !
b00 "
0#
0$
b00 %
b010 &
b00 '
b00 (
0)
b00 *
0+
b010 ,
0-
b0000 .
0/
00
b0000 1
02
03
b0000 4
05
#20000000
b01 !
1#
b10 %
b100 &
b01 '
1)
b10 *
b100 ,
1-
b0100 .
10
b0100 1
12
13
b0100 4
#40000000
b10 !
0#
b10 '
0)
0-
b1000 .
00
b1000 1
03
b1000 4
#60000000
b11 !
1#
1$
b00 %
b11 '
1)
b00 *
1+
1-
b1100 .
1/
10
b1100 1
02
13
b1100 4
#80000000
b00 !
b01 "
0#
0$
b01 %
b001 &
b00 '
b01 (
0)
b01 *
0+
b001 ,
0-
b0001 .
0/
00
b0001 1
03
b0001 4
15
#100000000
b01 !
1#
b11 %
b010 &
b01 '
1)
b11 *
b010 ,
1-
b0101 .
10
b0101 1
12
13
b0101 4
#120000000
b10 !
0#
b100 &
b10 '
0)
b100 ,
0-
b1001 .
00
b1001 1
03
b1001 4
#140000000
b11 !
1#
1$
b01 %
b11 '
1)
b01 *
1+
1-
b1101 .
1/
10
b1101 1
02
13
b1101 4
#160000000
b00 !
b10 "
0#
0$
b10 %
b001 &
b00 '
b10 (
0)
b10 *
0+
b001 ,
0-
b0010 .
0/
00
b0010 1
12
03
b0010 4
05
#180000000
b01 !
1#
1$
b00 %
b01 '
1)
b00 *
1+
1-
b0110 .
1/
10
b0110 1
02
13
b0110 4
#200000000
b10 !
0#
b010 &
b10 '
0)
b010 ,
0-
b1010 .
00
b1010 1
03
b1010 4
#220000000
b11 !
1#
b10 %
b100 &
b11 '
1)
b10 *
b100 ,
1-
b1110 .
10
b1110 1
12
13
b1110 4
#240000000
b00 !
b11 "
0#
0$
b11 %
b001 &
b00 '
b11 (
0)
b11 *
0+
b001 ,
0-
b0011 .
0/
00
b0011 1
03
b0011 4
15
#260000000
b01 !
1#
1$
b01 %
b01 '
1)
b01 *
1+
1-
b0111 .
1/
10
b0111 1
02
13
b0111 4
#280000000
b10 !
0#
b10 '
0)
0-
b1011 .
00
b1011 1
03
b1011 4
#300000000
b11 !
1#
b11 %
b010 &
b11 '
1)
b11 *
b010 ,
1-
b1111 .
10
b1111 1
12
13
b1111 4
